cli/__init__.py
cli/cli.py
crystal_clear/__init__.py
crystal_clear/clients/__init__.py
crystal_clear/clients/allium_client.py
crystal_clear/clients/base_client.py
crystal_clear/clients/etherscan_client.py
crystal_clear/clients/models.py
crystal_clear/clients/sourcify_client.py
crystal_clear/code_analyzer/__init__.py
crystal_clear/code_analyzer/analyzer.py
crystal_clear/code_analyzer/permissions.py
crystal_clear/code_analyzer/proxy.py
crystal_clear/traces/__init__.py
crystal_clear/traces/adapters/__init__.py
crystal_clear/traces/adapters/trace_normalizer.py
crystal_clear/traces/models.py
crystal_clear/traces/simulation_collector.py
crystal_clear/traces/trace_collector.py
crystal_clear/wrapper.py
mab_crystal_clear-1.0.8.dist-info/METADATA
mab_crystal_clear-1.0.8.dist-info/WHEEL
mab_crystal_clear-1.0.8.dist-info/entry_points.txt
mab_crystal_clear-1.0.8.dist-info/licenses/LICENSE
mab_crystal_clear-1.0.8.dist-info/RECORD
