Metadata-Version: 2.4
Name: mab-crystal-clear
Version: 1.0.8
Summary: Crystal-Clear CLI: Smart Contract Supply Chain Tool
License: MIT
License-File: LICENSE
Author: Monica Jin
Author-email: monicachenjin@gmail.com
Requires-Python: >3.12.0,<4
Classifier: License :: OSI Approved :: MIT License
Classifier: Programming Language :: Python :: 3
Classifier: Programming Language :: Python :: 3.13
Classifier: Programming Language :: Python :: 3.14
Requires-Dist: click (>=8.1.8,<9.0.0)
Requires-Dist: eth-utils (>=5.2.0,<6.0.0)
Requires-Dist: pytest (>=8.4.2,<9.0.0)
Requires-Dist: rich (>=14.1.0,<15.0.0)
Requires-Dist: uschunter (==0.0.1)
Requires-Dist: web3[tester] (>=7.8.0,<8.0.0)
